{
    "op1" : [
        {"desc":"15.5+2.5cm", "price" : "99900"},
        {"desc":"16.5+2.5cm", "price" : ""},
        {"desc":"17.5+2.5cm (+3,000원)", "price" : "102900"},
        {"desc":"18.5+2.5cm (+6,000원)", "price" : "105900"},
        {"desc":"19.5+2.5cm (+9,000원)", "price" : "108900"}
    ],
    "op2" : [
        {"desc":"15.5+2.5cm (+41,900원)", "price" : "141800"},
        {"desc":"16.5+2.5cm (+41,900원)", "price" : "141800"},
        {"desc":"17.5+2.5cm  (+45,900원)", "price" : "181800"},
        {"desc":"18.5+2.5cm (+49,900원)", "price" : "221800"},
        {"desc":"19.5+2.5cm (+53,900원)", "price" : "261900"}
    ]
}